langchain_stack_overflow_for_teams/__init__.py
langchain_stack_overflow_for_teams/loader.py
langchain_stack_overflow_for_teams-0.1.2.dist-info/METADATA
langchain_stack_overflow_for_teams-0.1.2.dist-info/WHEEL
langchain_stack_overflow_for_teams-0.1.2.dist-info/licenses/LICENSE
langchain_stack_overflow_for_teams-0.1.2.dist-info/RECORD
