Metadata-Version: 2.4
Name: langchain-stack-overflow-for-teams
Version: 0.1.2
Summary: LangChain integrations for Stack Overflow for Teams
Project-URL: Homepage, https://github.com/stackexchange/langchain-stack-overflow-for-teams
Project-URL: Issues, https://github.com/stackexchange/langchain-stack-overflow-for-teams/issues
License-Expression: Apache-2.0
License-File: LICENSE
Requires-Python: <4.0.0,>=3.10
Requires-Dist: backoff>=2.2.1
Requires-Dist: langchain-community<1.0.0,>=0.3.0
Requires-Dist: langchain-core<1.0.0,>=0.1.1
Requires-Dist: requests<3.0.0,>=2.0.0
